oxhttp-0.2.8.dist-info/METADATA
oxhttp-0.2.8.dist-info/WHEEL
oxhttp-0.2.8.dist-info/licenses/LICENSE
oxhttp/__init__.py
oxhttp/oxhttp.cpython-313-arm-linux-gnueabihf.so
oxhttp-0.2.8.dist-info/RECORD
