Metadata-Version: 2.4
Name: oxhttp
Version: 0.2.8
Classifier: Programming Language :: Rust
Classifier: Programming Language :: Python :: Implementation :: CPython
Classifier: Programming Language :: Python :: Implementation :: PyPy
Requires-Dist: orjson>=3.10.15
License-File: LICENSE
Summary: OxHttp is http server for python build in rust
Requires-Python: >=3.8
